{"runners":[{"id":"org.komga","name":"Komga","version":1.17,"minSupportedAppVersion":"6.0.0","thumbnail":"komga.png","website":"https://komga.org","supportedLanguages":["UNIVERSAL"],"rating":0,"path":"komga","environment":"source","hash":"c23e94425d890c1bb3c24798a233027b85086555fe69a43326ed74424f2771d6"},{"id":"org.suwayomi","name":"Suwayomi","version":1.1,"minSupportedAppVersion":"6.0.0","thumbnail":"suwayomi.png","website":"https://github.com/Suwayomi","supportedLanguages":["UNIVERSAL"],"rating":0,"path":"suwayomi","environment":"source","hash":"bba3f5a9b42e5fae2b40bef3133b40f8409d6f3358d170605785206bc7f8e8ed"},{"id":"zh.copymanga","name":"拷贝漫画","version":1.2,"website":"https://www.mangacopy.com/","supportedLanguages":["zh"],"thumbnail":"copymanga.png","minSupportedAppVersion":"5.0","rating":1,"path":"zh.copymanga","environment":"source","hash":"f5b3834273f891784c23421c809723f256ab7036d5adf984f3982e12977e623c"}],"listName":"everpcpc's List"}