{"runners":[{"id":"org.komga","name":"Komga","version":1.18,"minSupportedAppVersion":"6.0.0","thumbnail":"komga.png","website":"https://komga.org","supportedLanguages":["UNIVERSAL"],"rating":0,"path":"komga","environment":"source","hash":"7a76a64e96fba59b8a56caf69afe864728469c52817380e6091bd7fa5beaf7b3"},{"id":"org.suwayomi","name":"Suwayomi","version":1.2,"minSupportedAppVersion":"6.0.0","thumbnail":"suwayomi.png","website":"https://github.com/Suwayomi","supportedLanguages":["UNIVERSAL"],"rating":0,"path":"suwayomi","environment":"source","hash":"108d64c6a5ae323a6c011963f616410c5f818ab43da75057443a547309677bfe"},{"id":"zh.copymanga","name":"拷贝漫画","version":1.2,"website":"https://www.mangacopy.com/","supportedLanguages":["zh"],"thumbnail":"copymanga.png","minSupportedAppVersion":"5.0","rating":1,"path":"zh.copymanga","environment":"source","hash":"beb6f9ff48a1daf5fb4724bb82b82ba0d510403b0c72e15c6d639bcb223ab9c3"}],"listName":"everpcpc's List"}